sheepbackups-0.0.9.dist-info/DESCRIPTION.rst
sheepbackups-0.0.9.dist-info/METADATA
sheepbackups-0.0.9.dist-info/RECORD
sheepbackups-0.0.9.dist-info/WHEEL
sheepbackups-0.0.9.dist-info/entry_points.txt
sheepbackups-0.0.9.dist-info/metadata.json
sheepbackups-0.0.9.dist-info/top_level.txt
sheepcore/__init__.py
sheepcore/api.py
sheepcore/configcheck.py
sheepcore/exceptions.py
sheepcore/humanize.py
sheepcore/parser.py
sheepcore/run.py
sheepcore/schedule.py
sheepcore/tools.py
sheepcore/upload.py
sheepcore/utils.py
sheepcore/version.py
sheepcore/options/__init__.py
sheepcore/options/db.py
sheepcore/options/files.py
