Metadata-Version: 2.0
Name: sheepbackups
Version: 0.0.9
Summary: Python CLI for Sheepbackups
Home-page: https://github.com/sheepbackups
Author: Sheep Backups
Author-email: admin@sheepbackups.com
License: MIT
Keywords: backups development
Platform: UNKNOWN
Classifier: Development Status :: 3 - Alpha
Classifier: Intended Audience :: Developers
Classifier: Topic :: Software Development :: Build Tools
Classifier: License :: OSI Approved :: MIT License
Classifier: Programming Language :: Python :: 3
Classifier: Programming Language :: Python :: 3.3
Classifier: Programming Language :: Python :: 3.4
Classifier: Programming Language :: Python :: 3.5
Requires-Dist: boto3
Requires-Dist: delegator.py
Requires-Dist: pyyaml
Requires-Dist: requests
Requires-Dist: tabulate
